README.txt
setup.py
nonneg_rescal/__init__.py
nonneg_rescal/nonneg_rescal.py
nonneg_rescal.egg-info/PKG-INFO
nonneg_rescal.egg-info/SOURCES.txt
nonneg_rescal.egg-info/dependency_links.txt
nonneg_rescal.egg-info/requires.txt
nonneg_rescal.egg-info/top_level.txt