Metadata-Version: 2.1
Name: nonneg-rescal
Version: 0.1.0
Summary: non-negative RESCAL Tensor-Factorization
Home-page: https://github.com/bkj/nonneg_rescal
Author: Denis Krompass
Author-email: dekromp@gmail.com
License: BSD3
Keywords: non-negative,tensor,factorization,rescal
Platform: UNKNOWN
